pythorm/__init__.py
pythorm/main.py
pythorm-0.0.1.dist-info/LICENSE
pythorm-0.0.1.dist-info/METADATA
pythorm-0.0.1.dist-info/WHEEL
pythorm-0.0.1.dist-info/top_level.txt
pythorm-0.0.1.dist-info/RECORD
