Metadata-Version: 2.1
Name: pythorm
Version: 0.0.1
Summary: Asnyc ORM library for python
Author-email: Fenish <sohretalhadev@gmail.com>
Project-URL: Homepage, https://github.com/Fenish/pythorm
Project-URL: Bug Tracker, https://github.com/Fenish/pythorm/issues
Classifier: Programming Language :: Python :: 3
Classifier: License :: OSI Approved :: MIT License
Classifier: Operating System :: OS Independent
Requires-Python: >=3.9
License-File: LICENSE
Requires-Dist: aiomysql
